{
  "type": "bubble",
  "size": "kilo",
  "body": {
    "type": "box",
    "layout": "vertical",
    "spacing": "md",
    "contents": [
      {
        "type": "text",
        "text": "ติดต่อเรา",
        "weight": "bold",
        "size": "lg",
        "align": "center"
      },
      {
        "type": "button",
        "action": {
          "type": "uri",
          "label": "โทรหา",
          "uri": "tel:{{CONTACT_PHONE}}"
        },
        "style": "primary",
        "color": "#1DB446"
      },
      {
        "type": "button",
        "action": {
          "type": "uri",
          "label": "อีเมล",
          "uri": "mailto:{{CONTACT_EMAIL}}"
        },
        "style": "primary",
        "color": "#0072C6"
      },
      {
        "type": "button",
        "action": {
          "type": "message",
          "label": "รอการตอบกลับข้อความ",
          "text": "รอการตอบกลับข้อความ"
        },
        "style": "secondary"
      }
    ]
  }
}
